README.rst
setup.py
django_pyodbc_gis/__init__.py
django_pyodbc_gis/base.py
django_pyodbc_gis/compiler.py
django_pyodbc_gis/creation.py
django_pyodbc_gis/introspection.py
django_pyodbc_gis/operations.py
django_pyodbc_gis.egg-info/PKG-INFO
django_pyodbc_gis.egg-info/SOURCES.txt
django_pyodbc_gis.egg-info/dependency_links.txt
django_pyodbc_gis.egg-info/requires.txt
django_pyodbc_gis.egg-info/top_level.txt