Metadata-Version: 1.1
Name: django-pyodbc-gis
Version: 0.0.7
Summary: GIS support for SQL Server, on top of django-pyodbc-azure
Home-page: https://www.github.com/condense/django-pyodbc-gis
Author: Mark Hepburn
Author-email: mark@condense.com.au
License: BSD
Keywords: django mssql gis
Platform: UNKNOWN
Classifier: Development Status :: 1 - Planning
Classifier: Topic :: Database
Classifier: License :: OSI Approved :: BSD License
